dzdk.py
dzdk-0.1.0.dist-info/METADATA
dzdk-0.1.0.dist-info/WHEEL
dzdk-0.1.0.dist-info/entry_points.txt
dzdk-0.1.0.dist-info/licenses/LICENSE
dzdk-0.1.0.dist-info/RECORD
