Metadata-Version: 2.4
Name: dzdk
Version: 0.1.0
Summary: Dzaleka Digital Heritage CLI - A command-line interface for interacting with the Dzaleka Digital Heritage API
Project-URL: Homepage, https://github.com/Dzaleka-Connect/dzdk-cli
Project-URL: Documentation, https://services.dzaleka.com/docs/dzdk-cli
Project-URL: Repository, https://github.com/Dzaleka-Connect/dzdk-cli.git
Project-URL: Issues, https://github.com/Dzaleka-Connect/dzdk-cli/issues
Author-email: Bakari <bakari@mail.dzaleka.com>
License-Expression: MIT
License-File: LICENSE
Classifier: Development Status :: 4 - Beta
Classifier: Environment :: Console
Classifier: Intended Audience :: End Users/Desktop
Classifier: License :: OSI Approved :: MIT License
Classifier: Programming Language :: Python :: 3
Classifier: Programming Language :: Python :: 3.8
Classifier: Programming Language :: Python :: 3.9
Classifier: Programming Language :: Python :: 3.10
Classifier: Programming Language :: Python :: 3.11
Classifier: Topic :: Utilities
Requires-Python: >=3.8
Requires-Dist: click>=8.0.0
Requires-Dist: pandas>=1.3.0
Requires-Dist: prompt-toolkit>=3.0.0
Requires-Dist: pyyaml>=6.0
Requires-Dist: requests>=2.25.0
Requires-Dist: rich>=10.0.0
Requires-Dist: tabulate>=0.8.9
